mplStrater/__init__.py
mplStrater/data.py
mplStrater/strata.py
mplStrater-0.0.5.dist-info/LICENSE
mplStrater-0.0.5.dist-info/METADATA
mplStrater-0.0.5.dist-info/WHEEL
mplStrater-0.0.5.dist-info/top_level.txt
mplStrater-0.0.5.dist-info/RECORD
