Metadata-Version: 2.1
Name: mplStrater
Version: 0.0.5
Summary: plot geologic stratigraphic columns with python
Home-page: https://github.com/giocaizzi/mplStrater
Author: giocaizzi
Author-email: giocaizzi@gmail.com
License: MIT
Project-URL: Documentation, https://giocaizzi.github.io/mplStrater/
Project-URL: Bug Reports, https://github.com/giocaizzi/mplStrater/issues
Project-URL: Source, https://github.com/giocaizzi/mplStrater
Platform: UNKNOWN
Classifier: License :: OSI Approved :: MIT License
Classifier: Programming Language :: Python :: 3
Classifier: Programming Language :: Python :: 3.7
Classifier: Programming Language :: Python :: 3.8
Classifier: Programming Language :: Python :: 3.9
License-File: LICENSE
Requires-Dist: geopandas
Requires-Dist: matplotlib
Requires-Dist: numpy (>=1.17)
Requires-Dist: pandas
Requires-Dist: rasterio
Requires-Dist: rio-color
Provides-Extra: dev
Provides-Extra: docs
Requires-Dist: sphinx ; extra == 'docs'
Requires-Dist: nbsphinx ; extra == 'docs'
Requires-Dist: myst-parser ; extra == 'docs'
Requires-Dist: sphinx-rtd-theme ; extra == 'docs'
Provides-Extra: test
Requires-Dist: pytest ; extra == 'test'
Requires-Dist: pytest-cov ; extra == 'test'
